my_package/__init__.py
my_package/main.py
nano_shark_package-0.1.0.dist-info/METADATA
nano_shark_package-0.1.0.dist-info/WHEEL
nano_shark_package-0.1.0.dist-info/top_level.txt
nano_shark_package-0.1.0.dist-info/RECORD
