Metadata-Version: 2.1
Name: nano-shark-package
Version: 0.1.0
Summary: A small example package
Author-email: nanoshark <nanoshark@gmail.com>
License: MIT
Project-URL: Homepage, https://dev.azure.com/training/nano-shark-pypi
Project-URL: Bug Tracker, https://dev.azure.com/training/nano-shark-pypi/_workitems
Classifier: Programming Language :: Python :: 3
Classifier: License :: OSI Approved :: MIT License
Classifier: Operating System :: OS Independent
Requires-Python: >=3.8
Provides-Extra: dev
Requires-Dist: pytest>=7.0.0; extra == "dev"
Requires-Dist: pytest-cov>=4.0.0; extra == "dev"
